{
  "project_info": {
    "project_number": "807965102763",
    "firebase_url": "https://wordsofwisdom-quote.firebaseio.com",
    "project_id": "wordsofwisdom-quote",
    "storage_bucket": "wordsofwisdom-quote.appspot.com"
  },
  "client": [
    {
      "client_info": {
        "mobilesdk_app_id": "1:807965102763:android:41d76b806ff0af9e09ddee",
        "android_client_info": {
          "package_name": "com.quotes.wordsofwisdom"
        }
      },
      "oauth_client": [
        {
          "client_id": "807965102763-pf0kseq4q2m3nqueqijr8biokpuqk47g.apps.googleusercontent.com",
          "client_type": 1,
          "android_info": {
            "package_name": "com.quotes.wordsofwisdom",
            "certificate_hash": "975a0b21d6191796350ea9a09a9e16341593ca03"
          }
        },
        {
          "client_id": "807965102763-odg81ht41fhqmni6u6c4aspkg8eeptvg.apps.googleusercontent.com",
          "client_type": 3
        }
      ],
      "api_key": [
        {
          "current_key": "AIzaSyAzkQkCV9QexFuFQK2ApTni9_OJ_yznl8U"
        }
      ],
      "services": {
        "appinvite_service": {
          "other_platform_oauth_client": [
            {
              "client_id": "807965102763-odg81ht41fhqmni6u6c4aspkg8eeptvg.apps.googleusercontent.com",
              "client_type": 3
            },
            {
              "client_id": "807965102763-q8k9e4angmrikoffftgi3043aloe6u1u.apps.googleusercontent.com",
              "client_type": 2,
              "ios_info": {
                "bundle_id": "com.quotes.wordsofwisdom"
              }
            }
          ]
        }
      }
    }
  ],
  "configuration_version": "1"
}